rips/__init__.py
rips/case.py
rips/contour_map.py
rips/exception.py
rips/grid.py
rips/gridcasegroup.py
rips/grpc_retry_interceptor.py
rips/instance.py
rips/pdmobject.py
rips/plot.py
rips/project.py
rips/py.typed
rips/resinsight_classes.py
rips/retry_policy.py
rips/simulation_well.py
rips/surface.py
rips/view.py
rips/well_log_plot.py
rips/well_path.py
rips/well_path_collection.py
rips/generated/App_pb2.py
rips/generated/App_pb2_grpc.py
rips/generated/Case_pb2.py
rips/generated/Case_pb2_grpc.py
rips/generated/Commands_pb2.py
rips/generated/Commands_pb2_grpc.py
rips/generated/Definitions_pb2.py
rips/generated/Definitions_pb2_grpc.py
rips/generated/Grid_pb2.py
rips/generated/Grid_pb2_grpc.py
rips/generated/KeyValueStore_pb2.py
rips/generated/KeyValueStore_pb2_grpc.py
rips/generated/NNCProperties_pb2.py
rips/generated/NNCProperties_pb2_grpc.py
rips/generated/PdmObject_pb2.py
rips/generated/PdmObject_pb2_grpc.py
rips/generated/Project_pb2.py
rips/generated/Project_pb2_grpc.py
rips/generated/Properties_pb2.py
rips/generated/Properties_pb2_grpc.py
rips/generated/RiaVersionInfo.py
rips/generated/SimulationWell_pb2.py
rips/generated/SimulationWell_pb2_grpc.py
rips/generated/SimulatorTables_pb2.py
rips/generated/SimulatorTables_pb2_grpc.py
rips/generated/generated_classes.py
rips/tests/conftest.py
rips/tests/dataroot.py
rips/tests/test_cases.py
rips/tests/test_commands.py
rips/tests/test_completion_export.py
rips/tests/test_create_well_path.py
rips/tests/test_diameter_roughness_intervals.py
rips/tests/test_export_corner_point_grid.py
rips/tests/test_get_completion_data.py
rips/tests/test_grids.py
rips/tests/test_key_value_store.py
rips/tests/test_laterals.py
rips/tests/test_launch.py
rips/tests/test_msw_completion_data.py
rips/tests/test_nnc_properties.py
rips/tests/test_object_lifetime.py
rips/tests/test_pdmobject.py
rips/tests/test_polygon.py
rips/tests/test_project.py
rips/tests/test_properties.py
rips/tests/test_simulation_wells.py
rips/tests/test_summary_cases.py
rips-2025.12.0.1.dist-info/licenses/LICENSE
rips-2025.12.0.1.dist-info/METADATA
rips-2025.12.0.1.dist-info/WHEEL
rips-2025.12.0.1.dist-info/top_level.txt
rips-2025.12.0.1.dist-info/RECORD
