Metadata-Version: 2.4
Name: rips
Version: 2025.12.0.1
Summary: Python Interface for ResInsight
Home-page: http://www.resinsight.org
Author: Ceetron Solutions
Author-email: info@ceetronsolutions.com
License: Copyright (C) 2019-     Equinor ASA
Requires-Python: >=3.8
License-File: LICENSE
Requires-Dist: grpcio
Requires-Dist: protobuf
Requires-Dist: wheel
Requires-Dist: typing_extensions
Dynamic: author
Dynamic: author-email
Dynamic: description
Dynamic: home-page
Dynamic: license
Dynamic: license-file
Dynamic: requires-dist
Dynamic: requires-python
Dynamic: summary
